.DS_Store
geoapivietnam/__init__.py
geoapivietnam/main.py
geoapivietnam/main_backup.py
geoapivietnam/main_old.py
geoapivietnam/data/gso_province_district_ward.xlsx
geoapivietnam/data/valid_provinces.xlsx
geoapivietnam/data/~$gso_province_district_ward.xlsx
geoapivietnam-0.3.4.dist-info/LICENSE
geoapivietnam-0.3.4.dist-info/METADATA
geoapivietnam-0.3.4.dist-info/WHEEL
geoapivietnam-0.3.4.dist-info/top_level.txt
geoapivietnam-0.3.4.dist-info/RECORD
