Metadata-Version: 2.1
Name: geoapivietnam
Version: 0.3.4
Summary: Optimized Geo API for Vietnam
Home-page: https://github.com/tranngocminhhieu/geo-api-vietnam
Author: Tran Ngoc Minh Hieu
Author-email: tnmhieu@gmail.com
License-File: LICENSE
Requires-Dist: pandas
Requires-Dist: requests
Requires-Dist: geopy
Requires-Dist: tenacity
Requires-Dist: unidecode
Requires-Dist: openpyxl
Requires-Dist: appdirs
Requires-Dist: python-Levenshtein
Requires-Dist: fuzzywuzzy
